{
  "holly_striker": {
    "id": "holly_striker",
    "name": "Holly Striker",
    "tagline": "Standard issue holiday fury",
    "base_color": "#cc2244",
    "pattern_color": "#ffd700",
    "pattern_type": 4,
    "pattern_scale": 3.5,
    "metallic": 0.2,
    "roughness": 0.5,
    "bow_color": "#ffd700",
    "arm_color": "#f5f0e8",
    "arm_length": 0.55,
    "arm_thickness": 0.09,
    "leg_color": "#1a1a1a",
    "leg_length": 0.38,
    "leg_thickness": 0.1,
    "box_width": 1.0,
    "box_height": 1.15,
    "box_depth": 0.85,
    "expression": "determined",
    "max_hp": 120,
    "speed": 12.0,
    "fire_rate": 0.22,
    "damage": 14.0,
    "range": 15.0,
    "bullet_speed": 26.0,
    "shot_count": 1,
    "spread": 0.06,
    "pierce": 1,
    "unlock": "default",
    "topper": "none",
    "body_shape": "box",
    "accessory": "none"
  },
  "frostbite": {
    "id": "frostbite",
    "name": "Frostbite",
    "tagline": "Cold precision",
    "base_color": "#1a6699",
    "pattern_color": "#e8f4ff",
    "pattern_type": 5,
    "pattern_scale": 4.0,
    "metallic": 0.45,
    "roughness": 0.3,
    "bow_color": "#55ddff",
    "arm_color": "#b8ddff",
    "arm_length": 0.4,
    "arm_thickness": 0.07,
    "leg_color": "#0d3344",
    "leg_length": 0.32,
    "leg_thickness": 0.08,
    "box_width": 0.75,
    "box_height": 0.85,
    "box_depth": 0.7,
    "expression": "stoic",
    "max_hp": 80,
    "speed": 14.5,
    "fire_rate": 0.42,
    "damage": 28.0,
    "range": 19.0,
    "bullet_speed": 32.0,
    "shot_count": 1,
    "spread": 0.02,
    "pierce": 2,
    "unlock": "default",
    "topper": "antlers",
    "body_shape": "tall_rect",
    "accessory": "scarf"
  },
  "tangerine_terror": {
    "id": "tangerine_terror",
    "name": "Tangerine Terror",
    "tagline": "Citrus strike",
    "base_color": "#ff7722",
    "pattern_color": "#ffcc44",
    "pattern_type": 2,
    "pattern_scale": 5.0,
    "metallic": 0.4,
    "roughness": 0.35,
    "bow_color": "#ff4400",
    "arm_color": "#ffddaa",
    "arm_length": 0.5,
    "arm_thickness": 0.09,
    "leg_color": "#885522",
    "leg_length": 0.36,
    "leg_thickness": 0.1,
    "box_width": 0.92,
    "box_height": 1.0,
    "box_depth": 0.88,
    "expression": "cheerful",
    "max_hp": 115,
    "speed": 12.5,
    "fire_rate": 0.4,
    "damage": 21.0,
    "range": 15.0,
    "bullet_speed": 27.0,
    "shot_count": 3,
    "spread": 0.12,
    "pierce": 1,
    "unlock": "reach_wave_2",
    "topper": "bow_giant",
    "body_shape": "box",
    "accessory": "ribbon_tail"
  },
  "blizzard_box": {
    "id": "blizzard_box",
    "name": "Blizzard Box",
    "tagline": "The storm has a return address",
    "base_color": "#e8f0ff",
    "pattern_color": "#6699cc",
    "pattern_type": 5,
    "pattern_scale": 3.0,
    "metallic": 0.7,
    "roughness": 0.15,
    "bow_color": "#aaddff",
    "arm_color": "#ffffff",
    "arm_length": 0.45,
    "arm_thickness": 0.08,
    "leg_color": "#445566",
    "leg_length": 0.3,
    "leg_thickness": 0.09,
    "box_width": 0.9,
    "box_height": 0.95,
    "box_depth": 0.85,
    "expression": "stoic",
    "max_hp": 90,
    "speed": 13.0,
    "fire_rate": 0.28,
    "damage": 15.0,
    "range": 16.0,
    "bullet_speed": 25.0,
    "shot_count": 1,
    "spread": 0.05,
    "pierce": 1,
    "unlock": "reach_wave_3",
    "topper": "star",
    "body_shape": "cube",
    "accessory": "glow_aura"
  },
  "mistletoe": {
    "id": "mistletoe",
    "name": "Mistletoe",
    "tagline": "Kiss of death",
    "base_color": "#2d5a2d",
    "pattern_color": "#ff2255",
    "pattern_type": 2,
    "pattern_scale": 5.5,
    "metallic": 0.15,
    "roughness": 0.55,
    "bow_color": "#ff2255",
    "arm_color": "#88aa66",
    "arm_length": 0.52,
    "arm_thickness": 0.08,
    "leg_color": "#1a3a1a",
    "leg_length": 0.36,
    "leg_thickness": 0.09,
    "box_width": 0.9,
    "box_height": 1.0,
    "box_depth": 0.8,
    "expression": "stoic",
    "max_hp": 105,
    "speed": 13.5,
    "fire_rate": 0.32,
    "damage": 18.0,
    "range": 17.0,
    "bullet_speed": 28.0,
    "shot_count": 1,
    "spread": 0.04,
    "pierce": 3,
    "unlock": "reach_wave_4",
    "topper": "halo",
    "body_shape": "cylinder",
    "accessory": "tag"
  },
  "jingle_tank": {
    "id": "jingle_tank",
    "name": "Jingle Tank",
    "tagline": "Built like a stocking stuffer's nightmare",
    "base_color": "#2d8844",
    "pattern_color": "#ffdd44",
    "pattern_type": 3,
    "pattern_scale": 5.0,
    "metallic": 0.08,
    "roughness": 0.7,
    "bow_color": "#ff4466",
    "arm_color": "#ddd8c8",
    "arm_length": 0.65,
    "arm_thickness": 0.12,
    "leg_color": "#2a2a2a",
    "leg_length": 0.42,
    "leg_thickness": 0.14,
    "box_width": 1.3,
    "box_height": 1.4,
    "box_depth": 1.1,
    "expression": "angry",
    "max_hp": 280,
    "speed": 9.0,
    "fire_rate": 0.85,
    "damage": 32.0,
    "range": 11.0,
    "bullet_speed": 20.0,
    "shot_count": 4,
    "spread": 0.22,
    "pierce": 1,
    "unlock": "reach_wave_5",
    "topper": "santa_hat",
    "body_shape": "stacked_duo",
    "accessory": "none"
  },
  "sugarplum": {
    "id": "sugarplum",
    "name": "Sugarplum",
    "tagline": "Dances through danger",
    "base_color": "#cc33cc",
    "pattern_color": "#ffccff",
    "pattern_type": 4,
    "pattern_scale": 4.5,
    "metallic": 0.55,
    "roughness": 0.22,
    "bow_color": "#ff88dd",
    "arm_color": "#ffeeff",
    "arm_length": 0.48,
    "arm_thickness": 0.07,
    "leg_color": "#661866",
    "leg_length": 0.38,
    "leg_thickness": 0.08,
    "box_width": 0.78,
    "box_height": 0.92,
    "box_depth": 0.72,
    "expression": "cheerful",
    "max_hp": 75,
    "speed": 15.5,
    "fire_rate": 0.14,
    "damage": 11.0,
    "range": 14.0,
    "bullet_speed": 32.0,
    "shot_count": 1,
    "spread": 0.1,
    "pierce": 1,
    "unlock": "reach_wave_6",
    "topper": "candy_cane",
    "body_shape": "cube",
    "accessory": "ribbon_tail"
  },
  "gingerbrute": {
    "id": "gingerbrute",
    "name": "Gingerbrute",
    "tagline": "Baked with rage",
    "base_color": "#8b4513",
    "pattern_color": "#ffffff",
    "pattern_type": 7,
    "pattern_scale": 4.0,
    "metallic": 0.05,
    "roughness": 0.85,
    "bow_color": "#ff4466",
    "arm_color": "#d2691e",
    "arm_length": 0.7,
    "arm_thickness": 0.14,
    "leg_color": "#5c2a0a",
    "leg_length": 0.45,
    "leg_thickness": 0.15,
    "box_width": 1.35,
    "box_height": 1.45,
    "box_depth": 1.15,
    "expression": "angry",
    "max_hp": 320,
    "speed": 8.5,
    "fire_rate": 0.95,
    "damage": 38.0,
    "range": 10.0,
    "bullet_speed": 18.0,
    "shot_count": 5,
    "spread": 0.28,
    "pierce": 1,
    "unlock": "reach_wave_7",
    "topper": "none",
    "body_shape": "box",
    "accessory": "tag"
  },
  "nutcracker": {
    "id": "nutcracker",
    "name": "Nutcracker",
    "tagline": "Precision wrapped in tradition",
    "base_color": "#880022",
    "pattern_color": "#ffd700",
    "pattern_type": 3,
    "pattern_scale": 6.0,
    "metallic": 0.28,
    "roughness": 0.38,
    "bow_color": "#ffd700",
    "arm_color": "#f0d8a8",
    "arm_length": 0.6,
    "arm_thickness": 0.08,
    "leg_color": "#220000",
    "leg_length": 0.45,
    "leg_thickness": 0.09,
    "box_width": 0.85,
    "box_height": 1.35,
    "box_depth": 0.75,
    "expression": "determined",
    "max_hp": 110,
    "speed": 12.5,
    "fire_rate": 0.35,
    "damage": 20.0,
    "range": 18.0,
    "bullet_speed": 28.0,
    "shot_count": 2,
    "spread": 0.08,
    "pierce": 2,
    "unlock": "reach_wave_8",
    "topper": "ornament",
    "body_shape": "tall_rect",
    "accessory": "none"
  },
  "peppermint_hex": {
    "id": "peppermint_hex",
    "name": "Peppermint Hex",
    "tagline": "Spiraling into fire rate",
    "base_color": "#ffffff",
    "pattern_color": "#ff2244",
    "pattern_type": 1,
    "pattern_scale": 14.0,
    "metallic": 0.3,
    "roughness": 0.3,
    "bow_color": "#ff2244",
    "arm_color": "#ffffff",
    "arm_length": 0.5,
    "arm_thickness": 0.08,
    "leg_color": "#aa1122",
    "leg_length": 0.38,
    "leg_thickness": 0.09,
    "box_width": 0.85,
    "box_height": 1.0,
    "box_depth": 0.8,
    "expression": "manic",
    "max_hp": 85,
    "speed": 13.5,
    "fire_rate": 0.09,
    "damage": 9.0,
    "range": 14.5,
    "bullet_speed": 34.0,
    "shot_count": 2,
    "spread": 0.11,
    "pierce": 1,
    "unlock": "reach_wave_9",
    "topper": "halo",
    "body_shape": "cylinder",
    "accessory": "glow_aura"
  },
  "coal_breaker": {
    "id": "coal_breaker",
    "name": "Coal Breaker",
    "tagline": "Naughty list enforcer",
    "base_color": "#1a1a1a",
    "pattern_color": "#ff3344",
    "pattern_type": 1,
    "pattern_scale": 8.0,
    "metallic": 0.35,
    "roughness": 0.4,
    "bow_color": "#ff0044",
    "arm_color": "#888888",
    "arm_length": 0.58,
    "arm_thickness": 0.11,
    "leg_color": "#333333",
    "leg_length": 0.4,
    "leg_thickness": 0.12,
    "box_width": 1.1,
    "box_height": 1.25,
    "box_depth": 0.95,
    "expression": "cheerful",
    "max_hp": 180,
    "speed": 11.0,
    "fire_rate": 0.55,
    "damage": 22.0,
    "range": 14.0,
    "bullet_speed": 24.0,
    "shot_count": 3,
    "spread": 0.15,
    "pierce": 1,
    "unlock": "reach_wave_10",
    "topper": "none",
    "body_shape": "box",
    "accessory": "scarf"
  },
  "reindeer_fury": {
    "id": "reindeer_fury",
    "name": "Reindeer Fury",
    "tagline": "Antlers optional, rage mandatory",
    "base_color": "#663322",
    "pattern_color": "#ff8822",
    "pattern_type": 3,
    "pattern_scale": 5.5,
    "metallic": 0.1,
    "roughness": 0.75,
    "bow_color": "#ff6622",
    "arm_color": "#aa6633",
    "arm_length": 0.62,
    "arm_thickness": 0.1,
    "leg_color": "#331100",
    "leg_length": 0.5,
    "leg_thickness": 0.11,
    "box_width": 1.0,
    "box_height": 1.3,
    "box_depth": 0.9,
    "expression": "angry",
    "max_hp": 150,
    "speed": 13.5,
    "fire_rate": 0.26,
    "damage": 19.0,
    "range": 15.0,
    "bullet_speed": 30.0,
    "shot_count": 2,
    "spread": 0.1,
    "pierce": 1,
    "unlock": "reach_wave_11",
    "topper": "antlers",
    "body_shape": "box",
    "accessory": "none"
  },
  "yule_log": {
    "id": "yule_log",
    "name": "Yule Log",
    "tagline": "Burn bright, burn everything",
    "base_color": "#663300",
    "pattern_color": "#ff6600",
    "pattern_type": 1,
    "pattern_scale": 12.0,
    "metallic": 0.1,
    "roughness": 0.82,
    "bow_color": "#ff4400",
    "arm_color": "#aa8866",
    "arm_length": 0.5,
    "arm_thickness": 0.1,
    "leg_color": "#442200",
    "leg_length": 0.35,
    "leg_thickness": 0.11,
    "box_width": 1.4,
    "box_height": 0.85,
    "box_depth": 0.85,
    "expression": "angry",
    "max_hp": 200,
    "speed": 10.0,
    "fire_rate": 0.18,
    "damage": 6.0,
    "range": 10.0,
    "bullet_speed": 22.0,
    "shot_count": 1,
    "spread": 0.3,
    "pierce": 1,
    "unlock": "reach_wave_12",
    "topper": "none",
    "body_shape": "cylinder",
    "accessory": "scarf"
  },
  "garland_guardian": {
    "id": "garland_guardian",
    "name": "Garland Guardian",
    "tagline": "Woven protection",
    "base_color": "#1a6622",
    "pattern_color": "#ffdd44",
    "pattern_type": 4,
    "pattern_scale": 4.5,
    "metallic": 0.2,
    "roughness": 0.55,
    "bow_color": "#ff2244",
    "arm_color": "#aadd99",
    "arm_length": 0.55,
    "arm_thickness": 0.11,
    "leg_color": "#002200",
    "leg_length": 0.4,
    "leg_thickness": 0.12,
    "box_width": 1.05,
    "box_height": 1.2,
    "box_depth": 0.95,
    "expression": "determined",
    "max_hp": 200,
    "speed": 11.5,
    "fire_rate": 0.28,
    "damage": 17.0,
    "range": 16.0,
    "bullet_speed": 26.0,
    "shot_count": 1,
    "spread": 0.05,
    "pierce": 2,
    "unlock": "reach_wave_13",
    "topper": "star",
    "body_shape": "tall_rect",
    "accessory": "tag"
  },
  "snowglobe": {
    "id": "snowglobe",
    "name": "Snowglobe",
    "tagline": "A contained blizzard",
    "base_color": "#aaccee",
    "pattern_color": "#ffffff",
    "pattern_type": 5,
    "pattern_scale": 6.0,
    "metallic": 0.9,
    "roughness": 0.08,
    "bow_color": "#e8f4ff",
    "arm_color": "#f5f8ff",
    "arm_length": 0.44,
    "arm_thickness": 0.08,
    "leg_color": "#556677",
    "leg_length": 0.3,
    "leg_thickness": 0.09,
    "box_width": 0.95,
    "box_height": 0.95,
    "box_depth": 0.95,
    "expression": "stoic",
    "max_hp": 140,
    "speed": 11.0,
    "fire_rate": 0.45,
    "damage": 35.0,
    "range": 13.0,
    "bullet_speed": 22.0,
    "shot_count": 6,
    "spread": 0.35,
    "pierce": 1,
    "unlock": "reach_wave_14",
    "topper": "halo",
    "body_shape": "cube",
    "accessory": "glow_aura"
  },
  "candy_cannon": {
    "id": "candy_cannon",
    "name": "Candy Cannon",
    "tagline": "Sugar-coated devastation",
    "base_color": "#ff6688",
    "pattern_color": "#ffffff",
    "pattern_type": 6,
    "pattern_scale": 3.0,
    "metallic": 0.52,
    "roughness": 0.25,
    "bow_color": "#ff2255",
    "arm_color": "#ffe8ee",
    "arm_length": 0.52,
    "arm_thickness": 0.1,
    "leg_color": "#881133",
    "leg_length": 0.36,
    "leg_thickness": 0.11,
    "box_width": 1.05,
    "box_height": 1.1,
    "box_depth": 0.9,
    "expression": "cheerful",
    "max_hp": 100,
    "speed": 11.5,
    "fire_rate": 0.7,
    "damage": 45.0,
    "range": 17.0,
    "bullet_speed": 18.0,
    "shot_count": 1,
    "spread": 0.04,
    "pierce": 3,
    "unlock": "reach_wave_15",
    "topper": "candy_cane",
    "body_shape": "gift_bag",
    "accessory": "ribbon_tail"
  },
  "eggnog_warlord": {
    "id": "eggnog_warlord",
    "name": "Eggnog Warlord",
    "tagline": "Creamy, dreamy, deadly",
    "base_color": "#f5edca",
    "pattern_color": "#cc9944",
    "pattern_type": 7,
    "pattern_scale": 7.0,
    "metallic": 0.25,
    "roughness": 0.5,
    "bow_color": "#aa6633",
    "arm_color": "#ead8b0",
    "arm_length": 0.58,
    "arm_thickness": 0.11,
    "leg_color": "#553322",
    "leg_length": 0.42,
    "leg_thickness": 0.12,
    "box_width": 1.15,
    "box_height": 1.3,
    "box_depth": 1.0,
    "expression": "stoic",
    "max_hp": 220,
    "speed": 10.5,
    "fire_rate": 0.5,
    "damage": 28.0,
    "range": 13.5,
    "bullet_speed": 24.0,
    "shot_count": 2,
    "spread": 0.14,
    "pierce": 2,
    "unlock": "reach_wave_16",
    "topper": "santa_hat",
    "body_shape": "box",
    "accessory": "none"
  },
  "fruitcake_fatale": {
    "id": "fruitcake_fatale",
    "name": "Fruitcake Fatale",
    "tagline": "Nobody expects this",
    "base_color": "#884422",
    "pattern_color": "#ffaa44",
    "pattern_type": 6,
    "pattern_scale": 6.5,
    "metallic": 0.15,
    "roughness": 0.65,
    "bow_color": "#cc3366",
    "arm_color": "#ccaa77",
    "arm_length": 0.5,
    "arm_thickness": 0.1,
    "leg_color": "#442211",
    "leg_length": 0.36,
    "leg_thickness": 0.1,
    "box_width": 1.0,
    "box_height": 0.95,
    "box_depth": 0.9,
    "expression": "manic",
    "max_hp": 135,
    "speed": 11.0,
    "fire_rate": 0.6,
    "damage": 52.0,
    "range": 9.0,
    "bullet_speed": 16.0,
    "shot_count": 1,
    "spread": 0.02,
    "pierce": 4,
    "unlock": "reach_wave_17",
    "topper": "bow_giant",
    "body_shape": "stacked_duo",
    "accessory": "tag"
  },
  "angelic_strike": {
    "id": "angelic_strike",
    "name": "Angelic Strike",
    "tagline": "Divine wrapping",
    "base_color": "#f8f4e0",
    "pattern_color": "#ffd700",
    "pattern_type": 4,
    "pattern_scale": 4.0,
    "metallic": 0.75,
    "roughness": 0.18,
    "bow_color": "#ffd700",
    "arm_color": "#fff8dc",
    "arm_length": 0.52,
    "arm_thickness": 0.09,
    "leg_color": "#aa9944",
    "leg_length": 0.4,
    "leg_thickness": 0.1,
    "box_width": 1.0,
    "box_height": 1.2,
    "box_depth": 0.9,
    "expression": "determined",
    "max_hp": 160,
    "speed": 12.5,
    "fire_rate": 0.34,
    "damage": 24.0,
    "range": 18.0,
    "bullet_speed": 32.0,
    "shot_count": 1,
    "spread": 0.03,
    "pierce": 2,
    "unlock": "reach_wave_18",
    "topper": "halo",
    "body_shape": "box",
    "accessory": "glow_aura"
  },
  "star_tree_topper": {
    "id": "star_tree_topper",
    "name": "Star Tree Topper",
    "tagline": "Looks down on everyone",
    "base_color": "#ffe066",
    "pattern_color": "#ffffff",
    "pattern_type": 4,
    "pattern_scale": 5.5,
    "metallic": 0.92,
    "roughness": 0.1,
    "bow_color": "#ffeeaa",
    "arm_color": "#fff8dc",
    "arm_length": 0.46,
    "arm_thickness": 0.08,
    "leg_color": "#aa8844",
    "leg_length": 0.34,
    "leg_thickness": 0.09,
    "box_width": 0.88,
    "box_height": 1.05,
    "box_depth": 0.82,
    "expression": "stoic",
    "max_hp": 170,
    "speed": 12.0,
    "fire_rate": 0.38,
    "damage": 26.0,
    "range": 17.0,
    "bullet_speed": 28.0,
    "shot_count": 1,
    "spread": 0.04,
    "pierce": 3,
    "unlock": "reach_wave_19",
    "topper": "star",
    "body_shape": "tall_rect",
    "accessory": "ribbon_tail"
  },
  "ornament_prime": {
    "id": "ornament_prime",
    "name": "Ornament Prime",
    "tagline": "Decorative. Deadly.",
    "base_color": "#cc8800",
    "pattern_color": "#ffee88",
    "pattern_type": 4,
    "pattern_scale": 5.0,
    "metallic": 0.85,
    "roughness": 0.12,
    "bow_color": "#ffcc00",
    "arm_color": "#ffe8aa",
    "arm_length": 0.5,
    "arm_thickness": 0.08,
    "leg_color": "#664400",
    "leg_length": 0.36,
    "leg_thickness": 0.09,
    "box_width": 0.95,
    "box_height": 1.05,
    "box_depth": 0.95,
    "expression": "determined",
    "max_hp": 130,
    "speed": 12.0,
    "fire_rate": 0.3,
    "damage": 18.0,
    "range": 15.5,
    "bullet_speed": 26.0,
    "shot_count": 1,
    "spread": 0.05,
    "pierce": 1,
    "unlock": "reach_wave_20",
    "topper": "ornament",
    "body_shape": "cube",
    "accessory": "glow_aura"
  },
  "krampus_revenant": {
    "id": "krampus_revenant",
    "name": "Krampus Revenant",
    "tagline": "The boss became a box",
    "base_color": "#2a0010",
    "pattern_color": "#ff0033",
    "pattern_type": 4,
    "pattern_scale": 6.0,
    "metallic": 0.6,
    "roughness": 0.22,
    "bow_color": "#ff0033",
    "arm_color": "#553344",
    "arm_length": 0.68,
    "arm_thickness": 0.13,
    "leg_color": "#110008",
    "leg_length": 0.48,
    "leg_thickness": 0.14,
    "box_width": 1.25,
    "box_height": 1.5,
    "box_depth": 1.1,
    "expression": "angry",
    "max_hp": 350,
    "speed": 10.5,
    "fire_rate": 0.48,
    "damage": 48.0,
    "range": 16.0,
    "bullet_speed": 26.0,
    "shot_count": 3,
    "spread": 0.18,
    "pierce": 2,
    "unlock": "reach_wave_25",
    "topper": "antlers",
    "body_shape": "box",
    "accessory": "none"
  },
  "tinsel_rush": {
    "id": "tinsel_rush",
    "name": "Tinsel Rush",
    "tagline": "Too fast, too festive",
    "base_color": "#9922cc",
    "pattern_color": "#ffaadd",
    "pattern_type": 2,
    "pattern_scale": 6.0,
    "metallic": 0.6,
    "roughness": 0.2,
    "bow_color": "#ff88cc",
    "arm_color": "#f0e0f0",
    "arm_length": 0.48,
    "arm_thickness": 0.06,
    "leg_color": "#3a1a4a",
    "leg_length": 0.34,
    "leg_thickness": 0.07,
    "box_width": 0.7,
    "box_height": 0.8,
    "box_depth": 0.65,
    "expression": "manic",
    "max_hp": 65,
    "speed": 16.5,
    "fire_rate": 0.1,
    "damage": 8.0,
    "range": 13.0,
    "bullet_speed": 30.0,
    "shot_count": 1,
    "spread": 0.12,
    "pierce": 1,
    "unlock": "kill_100_enemies",
    "topper": "santa_hat",
    "body_shape": "cylinder",
    "accessory": "ribbon_tail"
  },
  "wassail_wraith": {
    "id": "wassail_wraith",
    "name": "Wassail Wraith",
    "tagline": "Spirits high, damage higher",
    "base_color": "#441166",
    "pattern_color": "#cc99ff",
    "pattern_type": 5,
    "pattern_scale": 3.5,
    "metallic": 0.7,
    "roughness": 0.18,
    "bow_color": "#aa66ff",
    "arm_color": "#eeddff",
    "arm_length": 0.45,
    "arm_thickness": 0.07,
    "leg_color": "#220044",
    "leg_length": 0.32,
    "leg_thickness": 0.08,
    "box_width": 0.82,
    "box_height": 1.1,
    "box_depth": 0.75,
    "expression": "manic",
    "max_hp": 90,
    "speed": 14.0,
    "fire_rate": 0.2,
    "damage": 16.0,
    "range": 18.5,
    "bullet_speed": 30.0,
    "shot_count": 1,
    "spread": 0.03,
    "pierce": 2,
    "unlock": "kill_250_enemies",
    "topper": "ornament",
    "body_shape": "gift_bag",
    "accessory": "tag"
  },
  "snowflake_sniper": {
    "id": "snowflake_sniper",
    "name": "Snowflake Sniper",
    "tagline": "Each shot unique",
    "base_color": "#0f2a44",
    "pattern_color": "#ccddff",
    "pattern_type": 5,
    "pattern_scale": 2.5,
    "metallic": 0.6,
    "roughness": 0.2,
    "bow_color": "#aaccff",
    "arm_color": "#e8f4ff",
    "arm_length": 0.38,
    "arm_thickness": 0.07,
    "leg_color": "#001022",
    "leg_length": 0.3,
    "leg_thickness": 0.08,
    "box_width": 0.7,
    "box_height": 0.8,
    "box_depth": 0.65,
    "expression": "stoic",
    "max_hp": 60,
    "speed": 14.0,
    "fire_rate": 0.72,
    "damage": 75.0,
    "range": 24.0,
    "bullet_speed": 40.0,
    "shot_count": 1,
    "spread": 0.0,
    "pierce": 5,
    "unlock": "kill_500_enemies",
    "topper": "star",
    "body_shape": "tall_rect",
    "accessory": "scarf"
  }
}